yesbenchmark/__init__.py
yesbenchmark/__main__.py
yesbenchmark/compute.py
yesbenchmark/core.py
yesbenchmark/darwin_shenanigans.py
yesbenchmark/exceptions.py
yesbenchmark/freq.py
yesbenchmark/main.py
yesbenchmark/resources.py
yesbenchmark/stress.py
yesbenchmark-1.0.0.post3.dist-info/licenses/LICENSE
yesbenchmark-1.0.0.post3.dist-info/METADATA
yesbenchmark-1.0.0.post3.dist-info/WHEEL
yesbenchmark-1.0.0.post3.dist-info/entry_points.txt
yesbenchmark-1.0.0.post3.dist-info/top_level.txt
yesbenchmark-1.0.0.post3.dist-info/RECORD
