Metadata-Version: 2.4
Name: yesbenchmark
Version: 1.0.0.post3
Summary: The only benchmark tool on the block crazy enough to abuse the UNIX yes command to test your CPU
Author-email: "Matthew Yang (杨佳明)" <matthew.yang204@gmail.com>
Maintainer-email: matthewyang204 <matthew.yang204@gmail.com>
License-Expression: GPL-3.0-or-later
Project-URL: Repository, https://github.com/matthewyang204/yesBenchMark
Project-URL: homepage, https://github.com/matthewyang204/yesBenchMark
Requires-Python: >=3.8
License-File: LICENSE
Requires-Dist: cowsay==6.1
Requires-Dist: psutil==7.2.1; platform_system != "Darwin"
Requires-Dist: yaspin==3.4.0
Dynamic: license-file
